[
    {
        "latitude":21.1466,
        "longitude":-86.82431
    },
    {
        "latitude":21.14881,
        "longitude":-86.82448
    },
    {
        "latitude":21.14909,
        "longitude":-86.82448
    },
    {
        "latitude":21.14925,
        "longitude":-86.82444
    },
    {
        "latitude":21.1496,
        "longitude":-86.82419
    },
    {
        "latitude":21.14971,
        "longitude":-86.82414
    },
    {
        "latitude":21.14986,
        "longitude":-86.82416
    },
    {
        "latitude":21.14997,
        "longitude":-86.82423
    },
    {
        "latitude":21.15027,
        "longitude":-86.82452
    },
    {
        "latitude":21.15039,
        "longitude":-86.82458
    },
    {
        "latitude":21.15058,
        "longitude":-86.82463
    },
    {
        "latitude":21.15104,
        "longitude":-86.82468
    },
    {
        "latitude":21.15162,
        "longitude":-86.82471
    },
    {
        "latitude":21.15313,
        "longitude":-86.82483
    },
    {
        "latitude":21.15368,
        "longitude":-86.82486
    },
    {
        "latitude":21.15478,
        "longitude":-86.82499
    },
    {
        "latitude":21.15589,
        "longitude":-86.82506
    },
    {
        "latitude":21.15619,
        "longitude":-86.82522
    },
    {
        "latitude":21.15647,
        "longitude":-86.82516
    },
    {
        "latitude":21.1566,
        "longitude":-86.8251
    },
    {
        "latitude":21.15685,
        "longitude":-86.82507
    },
    {
        "latitude":21.15698,
        "longitude":-86.82508
    },
    {
        "latitude":21.15711,
        "longitude":-86.82511
    },
    {
        "latitude":21.1573,
        "longitude":-86.82525
    },
    {
        "latitude":21.15741,
        "longitude":-86.82529
    },
    {
        "latitude":21.15755,
        "longitude":-86.82531
    },
    {
        "latitude":21.15772,
        "longitude":-86.82531
    },
    {
        "latitude":21.15792,
        "longitude":-86.82522
    },
    {
        "latitude":21.15812,
        "longitude":-86.82519
    },
    {
        "latitude":21.15882,
        "longitude":-86.82525
    },
    {
        "latitude":21.16007,
        "longitude":-86.82532
    },
    {
        "latitude":21.16112,
        "longitude":-86.82544
    },
    {
        "latitude":21.16273,
        "longitude":-86.82552
    },
    {
        "latitude":21.16305,
        "longitude":-86.82545
    },
    {
        "latitude":21.16331,
        "longitude":-86.82534
    },
    {
        "latitude":21.16348,
        "longitude":-86.82531
    },
    {
        "latitude":21.16366,
        "longitude":-86.82531
    },
    {
        "latitude":21.16383,
        "longitude":-86.82534
    },
    {
        "latitude":21.16422,
        "longitude":-86.82555
    },
    {
        "latitude":21.1645,
        "longitude":-86.82567
    },
    {
        "latitude":21.16469,
        "longitude":-86.8257
    },
    {
        "latitude":21.16518,
        "longitude":-86.82574
    },
    {
        "latitude":21.16547,
        "longitude":-86.82574
    },
    {
        "latitude":21.16577,
        "longitude":-86.82578
    },
    {
        "latitude":21.16822,
        "longitude":-86.82595
    },
    {
        "latitude":21.17033,
        "longitude":-86.82613
    },
    {
        "latitude":21.17068,
        "longitude":-86.82615
    },
    {
        "latitude":21.17117,
        "longitude":-86.82633
    },
    {
        "latitude":21.17134,
        "longitude":-86.82637
    },
    {
        "latitude":21.17304,
        "longitude":-86.82653
    },
    {
        "latitude":21.17326,
        "longitude":-86.82652
    },
    {
        "latitude":21.17341,
        "longitude":-86.82648
    },
    {
        "latitude":21.17355,
        "longitude":-86.82647
    },
    {
        "latitude":21.17371,
        "longitude":-86.82647
    },
    {
        "latitude":21.17401,
        "longitude":-86.82652
    },
    {
        "latitude":21.17411,
        "longitude":-86.82657
    },
    {
        "latitude":21.17428,
        "longitude":-86.82672
    },
    {
        "latitude":21.17432,
        "longitude":-86.82681
    },
    {
        "latitude":21.17477,
        "longitude":-86.82705
    },
    {
        "latitude":21.17602,
        "longitude":-86.82762
    },
    {
        "latitude":21.17696,
        "longitude":-86.82802
    },
    {
        "latitude":21.17721,
        "longitude":-86.82824
    },
    {
        "latitude":21.17726,
        "longitude":-86.82845
    },
    {
        "latitude":21.17731,
        "longitude":-86.82854
    },
    {
        "latitude":21.17743,
        "longitude":-86.82863
    },
    {
        "latitude":21.1781,
        "longitude":-86.82901
    },
    {
        "latitude":21.17887,
        "longitude":-86.82943
    },
    {
        "latitude":21.18138,
        "longitude":-86.83085
    },
    {
        "latitude":21.18238,
        "longitude":-86.83136
    },
    {
        "latitude":21.18268,
        "longitude":-86.83156
    },
    {
        "latitude":21.18295,
        "longitude":-86.8317
    },
    {
        "latitude":21.18419,
        "longitude":-86.83242
    },
    {
        "latitude":21.18587,
        "longitude":-86.83333
    },
    {
        "latitude":21.18769,
        "longitude":-86.83436
    },
    {
        "latitude":21.18764,
        "longitude":-86.83452
    },
    {
        "latitude":21.18741,
        "longitude":-86.83498
    },
    {
        "latitude":21.18664,
        "longitude":-86.83656
    },
    {
        "latitude":21.18655,
        "longitude":-86.8368
    },
    {
        "latitude":21.1862,
        "longitude":-86.83744
    },
    {
        "latitude":21.18555,
        "longitude":-86.83881
    },
    {
        "latitude":21.18516,
        "longitude":-86.83952
    },
    {
        "latitude":21.18482,
        "longitude":-86.84021
    },
    {
        "latitude":21.18419,
        "longitude":-86.84124
    },
    {
        "latitude":21.18374,
        "longitude":-86.84208
    },
    {
        "latitude":21.18258,
        "longitude":-86.84449
    },
    {
        "latitude":21.18212,
        "longitude":-86.84543
    },
    {
        "latitude":21.1819,
        "longitude":-86.84583
    },
    {
        "latitude":21.18189,
        "longitude":-86.84594
    },
    {
        "latitude":21.18152,
        "longitude":-86.84692
    },
    {
        "latitude":21.18094,
        "longitude":-86.84811
    },
    {
        "latitude":21.18089,
        "longitude":-86.84826
    },
    {
        "latitude":21.18078,
        "longitude":-86.84849
    },
    {
        "latitude":21.18026,
        "longitude":-86.84949
    },
    {
        "latitude":21.17986,
        "longitude":-86.85035
    },
    {
        "latitude":21.17967,
        "longitude":-86.8507
    },
    {
        "latitude":21.1791,
        "longitude":-86.85183
    },
    {
        "latitude":21.17715,
        "longitude":-86.85579
    },
    {
        "latitude":21.17664,
        "longitude":-86.85687
    },
    {
        "latitude":21.17633,
        "longitude":-86.85744
    },
    {
        "latitude":21.17546,
        "longitude":-86.85917
    },
    {
        "latitude":21.17357,
        "longitude":-86.86303
    },
    {
        "latitude":21.17314,
        "longitude":-86.86387
    },
    {
        "latitude":21.17235,
        "longitude":-86.86556
    },
    {
        "latitude":21.17172,
        "longitude":-86.86671
    },
    {
        "latitude":21.17116,
        "longitude":-86.86791
    },
    {
        "latitude":21.17034,
        "longitude":-86.86951
    },
    {
        "latitude":21.16919,
        "longitude":-86.87186
    },
    {
        "latitude":21.16924,
        "longitude":-86.87192
    },
    {
        "latitude":21.1701,
        "longitude":-86.87197
    },
    {
        "latitude":21.17103,
        "longitude":-86.87207
    },
    {
        "latitude":21.17196,
        "longitude":-86.87211
    },
    {
        "latitude":21.173,
        "longitude":-86.87219
    },
    {
        "latitude":21.17429,
        "longitude":-86.8724
    },
    {
        "latitude":21.17442,
        "longitude":-86.8724
    },
    {
        "latitude":21.17454,
        "longitude":-86.87243
    },
    {
        "latitude":21.17462,
        "longitude":-86.87249
    },
    {
        "latitude":21.17465,
        "longitude":-86.87257
    },
    {
        "latitude":21.17629,
        "longitude":-86.87347
    },
    {
        "latitude":21.17603,
        "longitude":-86.87394
    },
    {
        "latitude":21.17542,
        "longitude":-86.87523
    },
    {
        "latitude":21.1758,
        "longitude":-86.87545
    },
    {
        "latitude":21.1769,
        "longitude":-86.87606
    },
    {
        "latitude":21.17705,
        "longitude":-86.87584
    },
    {
        "latitude":21.17719,
        "longitude":-86.87559
    },
    {
        "latitude":21.1785,
        "longitude":-86.87295
    },
    {
        "latitude":21.17868,
        "longitude":-86.87303
    },
    {
        "latitude":21.18006,
        "longitude":-86.87379
    },
    {
        "latitude":21.1802,
        "longitude":-86.87385
    },
    {
        "latitude":21.17853,
        "longitude":-86.87733
    },
    {
        "latitude":21.178,
        "longitude":-86.87835
    },
    {
        "latitude":21.17696,
        "longitude":-86.88049
    },
    {
        "latitude":21.17656,
        "longitude":-86.88028
    },
    {
        "latitude":21.17582,
        "longitude":-86.87985
    },
    {
        "latitude":21.17562,
        "longitude":-86.87977
    },
    {
        "latitude":21.17524,
        "longitude":-86.87955
    },
    {
        "latitude":21.17526,
        "longitude":-86.87948
    },
    {
        "latitude":21.17602,
        "longitude":-86.87993
    },
    {
        "latitude":21.17693,
        "longitude":-86.88042
    },
    {
        "latitude":21.17705,
        "longitude":-86.8802
    },
    {
        "latitude":21.17783,
        "longitude":-86.87867
    },
    {
        "latitude":21.17804,
        "longitude":-86.8782
    },
    {
        "latitude":21.17853,
        "longitude":-86.87724
    },
    {
        "latitude":21.17974,
        "longitude":-86.87471
    },
    {
        "latitude":21.18012,
        "longitude":-86.87395
    },
    {
        "latitude":21.18011,
        "longitude":-86.87391
    },
    {
        "latitude":21.17959,
        "longitude":-86.87361
    },
    {
        "latitude":21.17864,
        "longitude":-86.8731
    },
    {
        "latitude":21.17856,
        "longitude":-86.87307
    },
    {
        "latitude":21.17848,
        "longitude":-86.87321
    },
    {
        "latitude":21.17824,
        "longitude":-86.87375
    },
    {
        "latitude":21.17795,
        "longitude":-86.87434
    },
    {
        "latitude":21.17739,
        "longitude":-86.87546
    },
    {
        "latitude":21.17701,
        "longitude":-86.87616
    },
    {
        "latitude":21.17687,
        "longitude":-86.8761
    },
    {
        "latitude":21.17618,
        "longitude":-86.87573
    },
    {
        "latitude":21.17574,
        "longitude":-86.87546
    },
    {
        "latitude":21.17559,
        "longitude":-86.87539
    },
    {
        "latitude":21.17532,
        "longitude":-86.87523
    },
    {
        "latitude":21.17616,
        "longitude":-86.87359
    },
    {
        "latitude":21.17501,
        "longitude":-86.87294
    },
    {
        "latitude":21.17458,
        "longitude":-86.87272
    },
    {
        "latitude":21.17448,
        "longitude":-86.87275
    },
    {
        "latitude":21.17441,
        "longitude":-86.87274
    },
    {
        "latitude":21.17432,
        "longitude":-86.87268
    },
    {
        "latitude":21.1742,
        "longitude":-86.87269
    },
    {
        "latitude":21.17393,
        "longitude":-86.87269
    },
    {
        "latitude":21.17359,
        "longitude":-86.87266
    },
    {
        "latitude":21.17274,
        "longitude":-86.87262
    },
    {
        "latitude":21.1717,
        "longitude":-86.87252
    },
    {
        "latitude":21.17073,
        "longitude":-86.87247
    },
    {
        "latitude":21.16997,
        "longitude":-86.8724
    },
    {
        "latitude":21.16945,
        "longitude":-86.8724
    },
    {
        "latitude":21.16923,
        "longitude":-86.87236
    },
    {
        "latitude":21.16912,
        "longitude":-86.87234
    },
    {
        "latitude":21.16909,
        "longitude":-86.87224
    },
    {
        "latitude":21.1691,
        "longitude":-86.87207
    },
    {
        "latitude":21.16909,
        "longitude":-86.87181
    },
    {
        "latitude":21.16974,
        "longitude":-86.87044
    },
    {
        "latitude":21.17023,
        "longitude":-86.86951
    },
    {
        "latitude":21.17051,
        "longitude":-86.86892
    },
    {
        "latitude":21.17113,
        "longitude":-86.86769
    },
    {
        "latitude":21.17184,
        "longitude":-86.86623
    },
    {
        "latitude":21.17264,
        "longitude":-86.86472
    },
    {
        "latitude":21.17297,
        "longitude":-86.86404
    },
    {
        "latitude":21.17409,
        "longitude":-86.86165
    },
    {
        "latitude":21.17473,
        "longitude":-86.8604
    },
    {
        "latitude":21.17558,
        "longitude":-86.85867
    },
    {
        "latitude":21.17625,
        "longitude":-86.85733
    },
    {
        "latitude":21.17784,
        "longitude":-86.85411
    },
    {
        "latitude":21.17873,
        "longitude":-86.85236
    },
    {
        "latitude":21.17959,
        "longitude":-86.85057
    },
    {
        "latitude":21.18044,
        "longitude":-86.84888
    },
    {
        "latitude":21.18145,
        "longitude":-86.84679
    },
    {
        "latitude":21.18179,
        "longitude":-86.84578
    },
    {
        "latitude":21.18228,
        "longitude":-86.84484
    },
    {
        "latitude":21.18261,
        "longitude":-86.84413
    },
    {
        "latitude":21.18366,
        "longitude":-86.84195
    },
    {
        "latitude":21.18402,
        "longitude":-86.84121
    },
    {
        "latitude":21.18471,
        "longitude":-86.84016
    },
    {
        "latitude":21.18511,
        "longitude":-86.83933
    },
    {
        "latitude":21.1856,
        "longitude":-86.83835
    },
    {
        "latitude":21.18588,
        "longitude":-86.83776
    },
    {
        "latitude":21.18615,
        "longitude":-86.83725
    },
    {
        "latitude":21.18642,
        "longitude":-86.83667
    },
    {
        "latitude":21.18651,
        "longitude":-86.83651
    },
    {
        "latitude":21.18687,
        "longitude":-86.83575
    },
    {
        "latitude":21.18756,
        "longitude":-86.83439
    },
    {
        "latitude":21.18732,
        "longitude":-86.83427
    },
    {
        "latitude":21.18589,
        "longitude":-86.83349
    },
    {
        "latitude":21.18462,
        "longitude":-86.83275
    },
    {
        "latitude":21.18245,
        "longitude":-86.83154
    },
    {
        "latitude":21.18171,
        "longitude":-86.8311
    },
    {
        "latitude":21.18127,
        "longitude":-86.83088
    },
    {
        "latitude":21.17999,
        "longitude":-86.83016
    },
    {
        "latitude":21.17844,
        "longitude":-86.82935
    },
    {
        "latitude":21.17756,
        "longitude":-86.82885
    },
    {
        "latitude":21.17721,
        "longitude":-86.82863
    },
    {
        "latitude":21.17713,
        "longitude":-86.8285
    },
    {
        "latitude":21.17709,
        "longitude":-86.82839
    },
    {
        "latitude":21.17707,
        "longitude":-86.82822
    },
    {
        "latitude":21.17705,
        "longitude":-86.82817
    },
    {
        "latitude":21.17648,
        "longitude":-86.82788
    },
    {
        "latitude":21.17539,
        "longitude":-86.82741
    },
    {
        "latitude":21.17506,
        "longitude":-86.82723
    },
    {
        "latitude":21.17469,
        "longitude":-86.82705
    },
    {
        "latitude":21.17423,
        "longitude":-86.82686
    },
    {
        "latitude":21.17403,
        "longitude":-86.82674
    },
    {
        "latitude":21.17309,
        "longitude":-86.82663
    },
    {
        "latitude":21.17218,
        "longitude":-86.82657
    },
    {
        "latitude":21.17145,
        "longitude":-86.82649
    },
    {
        "latitude":21.17128,
        "longitude":-86.82648
    },
    {
        "latitude":21.1709,
        "longitude":-86.82655
    },
    {
        "latitude":21.17048,
        "longitude":-86.82657
    },
    {
        "latitude":21.16924,
        "longitude":-86.82647
    },
    {
        "latitude":21.16856,
        "longitude":-86.82644
    },
    {
        "latitude":21.16648,
        "longitude":-86.82627
    },
    {
        "latitude":21.16476,
        "longitude":-86.82617
    },
    {
        "latitude":21.16405,
        "longitude":-86.82608
    },
    {
        "latitude":21.16389,
        "longitude":-86.82618
    },
    {
        "latitude":21.1638,
        "longitude":-86.82621
    },
    {
        "latitude":21.16357,
        "longitude":-86.82621
    },
    {
        "latitude":21.16334,
        "longitude":-86.82616
    },
    {
        "latitude":21.16322,
        "longitude":-86.82612
    },
    {
        "latitude":21.163,
        "longitude":-86.826
    },
    {
        "latitude":21.16251,
        "longitude":-86.82592
    },
    {
        "latitude":21.16086,
        "longitude":-86.82579
    },
    {
        "latitude":21.16039,
        "longitude":-86.82577
    },
    {
        "latitude":21.15913,
        "longitude":-86.82567
    },
    {
        "latitude":21.15788,
        "longitude":-86.82559
    },
    {
        "latitude":21.15764,
        "longitude":-86.82549
    },
    {
        "latitude":21.15724,
        "longitude":-86.82556
    },
    {
        "latitude":21.15688,
        "longitude":-86.82555
    },
    {
        "latitude":21.15656,
        "longitude":-86.82548
    },
    {
        "latitude":21.15633,
        "longitude":-86.82539
    },
    {
        "latitude":21.15626,
        "longitude":-86.82539
    },
    {
        "latitude":21.15611,
        "longitude":-86.82549
    },
    {
        "latitude":21.15412,
        "longitude":-86.82531
    },
    {
        "latitude":21.15337,
        "longitude":-86.82526
    },
    {
        "latitude":21.15287,
        "longitude":-86.82525
    },
    {
        "latitude":21.15208,
        "longitude":-86.82518
    },
    {
        "latitude":21.15121,
        "longitude":-86.82513
    },
    {
        "latitude":21.15096,
        "longitude":-86.82509
    },
    {
        "latitude":21.15071,
        "longitude":-86.82494
    },
    {
        "latitude":21.15051,
        "longitude":-86.82493
    },
    {
        "latitude":21.15011,
        "longitude":-86.82495
    },
    {
        "latitude":21.14925,
        "longitude":-86.82487
    },
    {
        "latitude":21.14807,
        "longitude":-86.82472
    },
    {
        "latitude":21.14783,
        "longitude":-86.82471
    },
    {
        "latitude":21.14769,
        "longitude":-86.82474
    },
    {
        "latitude":21.14751,
        "longitude":-86.82482
    },
    {
        "latitude":21.1473,
        "longitude":-86.82483
    },
    {
        "latitude":21.14651,
        "longitude":-86.82474
    },
    {
        "latitude":21.14632,
        "longitude":-86.82464
    },
    {
        "latitude":21.14595,
        "longitude":-86.82456
    },
    {
        "latitude":21.14573,
        "longitude":-86.82454
    },
    {
        "latitude":21.14445,
        "longitude":-86.82453
    },
    {
        "latitude":21.14436,
        "longitude":-86.82467
    },
    {
        "latitude":21.14429,
        "longitude":-86.82474
    },
    {
        "latitude":21.14421,
        "longitude":-86.8248
    },
    {
        "latitude":21.14404,
        "longitude":-86.82483
    },
    {
        "latitude":21.14394,
        "longitude":-86.82481
    },
    {
        "latitude":21.14383,
        "longitude":-86.82476
    },
    {
        "latitude":21.14374,
        "longitude":-86.82468
    },
    {
        "latitude":21.14366,
        "longitude":-86.82458
    },
    {
        "latitude":21.14362,
        "longitude":-86.82444
    },
    {
        "latitude":21.14361,
        "longitude":-86.82428
    },
    {
        "latitude":21.14366,
        "longitude":-86.82409
    },
    {
        "latitude":21.14389,
        "longitude":-86.82388
    },
    {
        "latitude":21.14398,
        "longitude":-86.82373
    },
    {
        "latitude":21.14402,
        "longitude":-86.82359
    },
    {
        "latitude":21.14403,
        "longitude":-86.82343
    },
    {
        "latitude":21.14408,
        "longitude":-86.82332
    },
    {
        "latitude":21.14419,
        "longitude":-86.82335
    },
    {
        "latitude":21.14447,
        "longitude":-86.8238
    },
    {
        "latitude":21.14472,
        "longitude":-86.82409
    },
    {
        "latitude":21.14488,
        "longitude":-86.82417
    },
    {
        "latitude":21.14545,
        "longitude":-86.82422
    },
    {
        "latitude":21.14629,
        "longitude":-86.82428
    }
]